toggle_button_set/__init__.py
toggle_button_set/example.py
toggle_button_set/frontend/build/asset-manifest.json
toggle_button_set/frontend/build/bootstrap.min.css
toggle_button_set/frontend/build/index.html
toggle_button_set/frontend/build/static/js/main.505afb56.js
toggle_button_set/frontend/build/static/js/main.505afb56.js.LICENSE.txt
toggle_button_set/frontend/build/static/js/main.505afb56.js.map
streamlit_toggle_button_set_improved-0.1.1.dist-info/LICENSE
streamlit_toggle_button_set_improved-0.1.1.dist-info/METADATA
streamlit_toggle_button_set_improved-0.1.1.dist-info/WHEEL
streamlit_toggle_button_set_improved-0.1.1.dist-info/top_level.txt
streamlit_toggle_button_set_improved-0.1.1.dist-info/RECORD
