Metadata-Version: 2.1
Name: streamlit-toggle-button-set-improved
Version: 0.1.1
Summary: A Streamlit component for toggle button sets (Fork)
Home-page: https://github.com/bensonbs/streamlit-toggle-button-set
Author: BensonBS
Author-email: benson.bs.sung@gmail.com
Classifier: Programming Language :: Python :: 3
Classifier: License :: OSI Approved :: MIT License
Classifier: Operating System :: OS Independent
Requires-Python: >=3.7
License-File: LICENSE
Requires-Dist: streamlit >=0.63
